torchqubo/__init__.py
torchqubo/cli.py
torchqubo/io.py
torchqubo/solvers.py
torchqubo/utils.py
torchqubo-0.1.0.dist-info/licenses/LICENSE
torchqubo-0.1.0.dist-info/METADATA
torchqubo-0.1.0.dist-info/WHEEL
torchqubo-0.1.0.dist-info/entry_points.txt
torchqubo-0.1.0.dist-info/top_level.txt
torchqubo-0.1.0.dist-info/RECORD
